helanal/__init__.py
helanal/helanal.py
helanal/data/README.md
helanal/data/__init__.py
helanal/data/files.py
helanal/data/mda.txt
helanal/tests/__init__.py
helanal/tests/conftest.py
helanal/tests/test_helanal.py
helanal/tests/utils.py
helanal-0.1.0.dist-info/AUTHORS.md
helanal-0.1.0.dist-info/LICENSE
helanal-0.1.0.dist-info/METADATA
helanal-0.1.0.dist-info/WHEEL
helanal-0.1.0.dist-info/top_level.txt
helanal-0.1.0.dist-info/RECORD
