Metadata-Version: 2.1
Name: helanal
Version: 0.1.0
Summary: A package to characterise the geometry of protein helicies.
Author-email: "Your name (or your organization/company/team)" <fiona@mdanalysis.org>
Maintainer-email: "Your name (or your organization/company/team)" <fiona@mdanalysis.org>
License: GNU GENERAL PUBLIC LICENSE
Keywords: molecular simulations
Requires-Python: >=3.9
License-File: LICENSE
License-File: AUTHORS.md
Requires-Dist: MDAnalysis >=2.0.0
Provides-Extra: doc
Requires-Dist: sphinx ; extra == 'doc'
Requires-Dist: sphinx-rtd-theme ; extra == 'doc'
Provides-Extra: test
Requires-Dist: pytest >=6.0 ; extra == 'test'
Requires-Dist: pytest-xdist >=2.5 ; extra == 'test'
Requires-Dist: pytest-cov >=3.0 ; extra == 'test'
Requires-Dist: MDAnalysisTests >=2.0.0 ; extra == 'test'
